sec_client/__init__.py
sec_client/base.py
sec_client/caller.py
sec_client/client.py
sec_client/dumper.py
sec_client/extractor.py
sec_client/loader.py
sec_client/tables/__init__.py
sec_client/tables/DATABASE.db
sec_client/tables/inputs.py
sec_client/tables/outputs.py
sec_client/tables/tables.py
sec_client-0.0.1.dist-info/LICENSE
sec_client-0.0.1.dist-info/WHEEL
sec_client-0.0.1.dist-info/METADATA
sec_client-0.0.1.dist-info/RECORD
